Metadata-Version: 1.0
Name: idioticapi
Version: 1.0.1
Summary: A simple idiot's guide api wrapper in python
Home-page: https://github.com/freetnt5852/idioticapi
Author: Free TNT & Umbresp
Author-email: darksoulgamer5852@gmail.com
License: MIT
Platform: UNKNOWN
